kafka_count.py
kafka_counter-0.0.2.dist-info/LICENSE
kafka_counter-0.0.2.dist-info/METADATA
kafka_counter-0.0.2.dist-info/WHEEL
kafka_counter-0.0.2.dist-info/entry_points.txt
kafka_counter-0.0.2.dist-info/top_level.txt
kafka_counter-0.0.2.dist-info/RECORD
