Metadata-Version: 2.1
Name: kafka-counter
Version: 0.0.2
Summary: Kafka message counter
Author-email: Sandip Bhattacharya <pypi@r.sandipb.net>
License: Apache-2.0
Project-URL: Homepage, https://github.com/sandipb/kafka-counter
Project-URL: Bug Tracker, https://github.com/sandipb/kafka-counter/issues
Keywords: kafka
Classifier: Development Status :: 3 - Alpha
Classifier: License :: OSI Approved :: Apache Software License
Classifier: Programming Language :: Python :: 3.7
Classifier: Programming Language :: Python :: 3.8
Classifier: Programming Language :: Python :: 3.9
Classifier: Topic :: Utilities
Requires-Python: >=3.7
License-File: LICENSE
Requires-Dist: pyaml
Requires-Dist: jsonpath-ng
Requires-Dist: kafka-python
Requires-Dist: python-snappy
